{"_note":"Representative sample — fictional IDs and amounts. Mirrors order_drafts + Stripe session structure.","order_draft_id":"draft-sample-uuid-0001","wa_id":"525512345678","customer_phone":"+52 55 1234 5678","market":"MX","currency":"USD","status":"checkout_pending","source":"whatsapp","items_snapshot":[{"name":"Starter Pack — 30 day supply","sku":"GBN-MX-SP-001","price":45.00,"quantity":2,"stripe_price_id":"price_SAMPLE_MX_001"}],"subtotal_amount":90.00,"shipping_amount":15.00,"total_amount":105.00,"quantity_total":2,"shipping_rule_version":"v2_tiered_flat","stripe_session_id":"cs_test_SAMPLE_SESSION_001","purchase_type":"one_time","created_at":"2026-05-14T18:30:00Z","updated_at":"2026-05-14T18:32:00Z"}
